mitanas/__init__.py
mitanas/mitanas.py
mitanas-0.0.2.dist-info/LICENSE
mitanas-0.0.2.dist-info/METADATA
mitanas-0.0.2.dist-info/WHEEL
mitanas-0.0.2.dist-info/top_level.txt
mitanas-0.0.2.dist-info/RECORD
