Metadata-Version: 2.1
Name: mitanas
Version: 0.0.2
Summary: Make IT AN Autostart Script
Home-page: https://github.com/andersonssh/mitanas
Author: Anderson Araújo
Author-email: andersondev.ssh@gmail.com
Classifier: Programming Language :: Python :: 3
Classifier: License :: OSI Approved :: MIT License
Classifier: Operating System :: OS Independent
Requires-Python: >=3.7
License-File: LICENSE
Requires-Dist: pyinstaller
